mlxcli/__init__.py
mlxcli/generate.py
mlxcli/main.py
mlxcli-0.1.7.dist-info/METADATA
mlxcli-0.1.7.dist-info/WHEEL
mlxcli-0.1.7.dist-info/entry_points.txt
mlxcli-0.1.7.dist-info/top_level.txt
mlxcli-0.1.7.dist-info/RECORD
